{
    "appKeys": {},
    "capabilities": [
        ""
    ],
    "companyName": "ameiga",
    "longName": "Pebble Stacker",
    "projectType": "native",
    "resources": {
        "media": [
            {
                "file": "images/ameiga_pebble_splash.png",
                "name": "AMEIGA_SPLASH",
                "type": "png"
            },
            {
                "file": "images/next_arrow.png",
                "name": "NEXT_ARROW",
                "type": "png"
            },
            {
                "file": "images/back_arrow.png",
                "name": "BACK_ARROW",
                "type": "png"
            },
            {
                "file": "images/front_arrow.png",
                "name": "FRONT_ARROW",
                "type": "png"
            },
            {
                "file": "images/PebbleStackerIcon3.png",
                "menuIcon": true,
                "name": "PEBBLE_STACKER_ICON",
                "type": "png"
            }
        ]
    },
    "shortName": "Stacker",
    "uuid": "52ed0ef1-7128-47fe-b1c5-935ce15852e2",
    "versionCode": 1,
    "versionLabel": "1.1",
    "watchapp": {
        "watchface": false
    }
}
